{
  "textures": [
    {
      "image": "Argus-0.png",
      "format": "RGBA8888",
      "size": {
        "w": 1993,
        "h": 1664
      },
      "scale": 1,
      "frames": [
        {
          "filename": "https://powers.s3.amazonaws.com/ArgusHit_000.png",
          "rotated": false,
          "trimmed": true,
          "sourceSize": {
            "w": 720,
            "h": 720
          },
          "spriteSourceSize": {
            "x": 260,
            "y": 201,
            "w": 188,
            "h": 472
          },
          "frame": {
            "x": 0,
            "y": 0,
            "w": 188,
            "h": 472
          }
        },
        {
          "filename": "https://powers.s3.amazonaws.com/ArgusDie_000.png",
          "rotated": false,
          "trimmed": true,
          "sourceSize": {
            "w": 720,
            "h": 720
          },
          "spriteSourceSize": {
            "x": 315,
            "y": 202,
            "w": 190,
            "h": 448
          },
          "frame": {
            "x": 188,
            "y": 0,
            "w": 190,
            "h": 448
          }
        },
        {
          "filename": "https://powers.s3.amazonaws.com/ArgusKick_001.png",
          "rotated": false,
          "trimmed": true,
          "sourceSize": {
            "w": 720,
            "h": 720
          },
          "spriteSourceSize": {
            "x": 296,
            "y": 206,
            "w": 191,
            "h": 463
          },
          "frame": {
            "x": 378,
            "y": 0,
            "w": 191,
            "h": 463
          }
        },
        {
          "filename": "https://powers.s3.amazonaws.com/ArgusIdle_000.png",
          "rotated": false,
          "trimmed": true,
          "sourceSize": {
            "w": 720,
            "h": 720
          },
          "spriteSourceSize": {
            "x": 270,
            "y": 196,
            "w": 195,
            "h": 474
          },
          "frame": {
            "x": 569,
            "y": 0,
            "w": 195,
            "h": 474
          }
        },
        {
          "filename": "https://powers.s3.amazonaws.com/ArgusIdle_001.png",
          "rotated": false,
          "trimmed": true,
          "sourceSize": {
            "w": 720,
            "h": 720
          },
          "spriteSourceSize": {
            "x": 269,
            "y": 196,
            "w": 196,
            "h": 474
          },
          "frame": {
            "x": 764,
            "y": 0,
            "w": 196,
            "h": 474
          }
        },
        {
          "filename": "https://powers.s3.amazonaws.com/ArgusIdle_002.png",
          "rotated": false,
          "trimmed": true,
          "sourceSize": {
            "w": 720,
            "h": 720
          },
          "spriteSourceSize": {
            "x": 268,
            "y": 196,
            "w": 197,
            "h": 474
          },
          "frame": {
            "x": 960,
            "y": 0,
            "w": 197,
            "h": 474
          }
        },
        {
          "filename": "https://powers.s3.amazonaws.com/ArgusIdle_003.png",
          "rotated": false,
          "trimmed": true,
          "sourceSize": {
            "w": 720,
            "h": 720
          },
          "spriteSourceSize": {
            "x": 267,
            "y": 196,
            "w": 198,
            "h": 474
          },
          "frame": {
            "x": 1157,
            "y": 0,
            "w": 198,
            "h": 474
          }
        },
        {
          "filename": "https://powers.s3.amazonaws.com/ArgusIdle_004.png",
          "rotated": false,
          "trimmed": true,
          "sourceSize": {
            "w": 720,
            "h": 720
          },
          "spriteSourceSize": {
            "x": 266,
            "y": 196,
            "w": 199,
            "h": 474
          },
          "frame": {
            "x": 1355,
            "y": 0,
            "w": 199,
            "h": 474
          }
        },
        {
          "filename": "https://powers.s3.amazonaws.com/ArgusKick2_001.png",
          "rotated": false,
          "trimmed": true,
          "sourceSize": {
            "w": 720,
            "h": 720
          },
          "spriteSourceSize": {
            "x": 286,
            "y": 206,
            "w": 219,
            "h": 464
          },
          "frame": {
            "x": 1554,
            "y": 0,
            "w": 219,
            "h": 464
          }
        },
        {
          "filename": "https://powers.s3.amazonaws.com/ArgusCast_001.png",
          "rotated": false,
          "trimmed": true,
          "sourceSize": {
            "w": 720,
            "h": 720
          },
          "spriteSourceSize": {
            "x": 268,
            "y": 202,
            "w": 220,
            "h": 471
          },
          "frame": {
            "x": 1773,
            "y": 0,
            "w": 220,
            "h": 471
          }
        },
        {
          "filename": "https://powers.s3.amazonaws.com/ArgusKick_000.png",
          "rotated": false,
          "trimmed": true,
          "sourceSize": {
            "w": 720,
            "h": 720
          },
          "spriteSourceSize": {
            "x": 236,
            "y": 213,
            "w": 227,
            "h": 451
          },
          "frame": {
            "x": 0,
            "y": 474,
            "w": 227,
            "h": 451
          }
        },
        {
          "filename": "https://powers.s3.amazonaws.com/ArgusCast_000.png",
          "rotated": false,
          "trimmed": true,
          "sourceSize": {
            "w": 720,
            "h": 720
          },
          "spriteSourceSize": {
            "x": 267,
            "y": 208,
            "w": 229,
            "h": 465
          },
          "frame": {
            "x": 227,
            "y": 474,
            "w": 229,
            "h": 465
          }
        },
        {
          "filename": "https://powers.s3.amazonaws.com/ArgusPunch2_000.png",
          "rotated": false,
          "trimmed": true,
          "sourceSize": {
            "w": 720,
            "h": 720
          },
          "spriteSourceSize": {
            "x": 233,
            "y": 214,
            "w": 230,
            "h": 459
          },
          "frame": {
            "x": 456,
            "y": 474,
            "w": 230,
            "h": 459
          }
        },
        {
          "filename": "https://powers.s3.amazonaws.com/ArgusPunch3_000.png",
          "rotated": false,
          "trimmed": true,
          "sourceSize": {
            "w": 720,
            "h": 720
          },
          "spriteSourceSize": {
            "x": 233,
            "y": 214,
            "w": 230,
            "h": 459
          },
          "frame": {
            "x": 686,
            "y": 474,
            "w": 230,
            "h": 459
          }
        },
        {
          "filename": "https://powers.s3.amazonaws.com/ArgusPunch3_001.png",
          "rotated": false,
          "trimmed": true,
          "sourceSize": {
            "w": 720,
            "h": 720
          },
          "spriteSourceSize": {
            "x": 259,
            "y": 203,
            "w": 236,
            "h": 470
          },
          "frame": {
            "x": 916,
            "y": 474,
            "w": 236,
            "h": 470
          }
        },
        {
          "filename": "https://powers.s3.amazonaws.com/ArgusPunch_000.png",
          "rotated": false,
          "trimmed": true,
          "sourceSize": {
            "w": 720,
            "h": 720
          },
          "spriteSourceSize": {
            "x": 233,
            "y": 214,
            "w": 239,
            "h": 459
          },
          "frame": {
            "x": 1152,
            "y": 474,
            "w": 239,
            "h": 459
          }
        },
        {
          "filename": "https://powers.s3.amazonaws.com/ArgusKick2_000.png",
          "rotated": false,
          "trimmed": true,
          "sourceSize": {
            "w": 720,
            "h": 720
          },
          "spriteSourceSize": {
            "x": 234,
            "y": 214,
            "w": 252,
            "h": 455
          },
          "frame": {
            "x": 1391,
            "y": 474,
            "w": 252,
            "h": 455
          }
        },
        {
          "filename": "https://powers.s3.amazonaws.com/ArgusPunch2_001.png",
          "rotated": false,
          "trimmed": true,
          "sourceSize": {
            "w": 720,
            "h": 720
          },
          "spriteSourceSize": {
            "x": 235,
            "y": 216,
            "w": 296,
            "h": 456
          },
          "frame": {
            "x": 1643,
            "y": 474,
            "w": 296,
            "h": 456
          }
        },
        {
          "filename": "https://powers.s3.amazonaws.com/ArgusDie_001.png",
          "rotated": false,
          "trimmed": true,
          "sourceSize": {
            "w": 720,
            "h": 720
          },
          "spriteSourceSize": {
            "x": 263,
            "y": 230,
            "w": 313,
            "h": 405
          },
          "frame": {
            "x": 0,
            "y": 944,
            "w": 313,
            "h": 405
          }
        },
        {
          "filename": "https://powers.s3.amazonaws.com/ArgusPunch_001.png",
          "rotated": false,
          "trimmed": true,
          "sourceSize": {
            "w": 720,
            "h": 720
          },
          "spriteSourceSize": {
            "x": 235,
            "y": 216,
            "w": 349,
            "h": 456
          },
          "frame": {
            "x": 313,
            "y": 944,
            "w": 349,
            "h": 456
          }
        },
        {
          "filename": "https://powers.s3.amazonaws.com/ArgusKick_002.png",
          "rotated": false,
          "trimmed": true,
          "sourceSize": {
            "w": 720,
            "h": 720
          },
          "spriteSourceSize": {
            "x": 264,
            "y": 200,
            "w": 358,
            "h": 462
          },
          "frame": {
            "x": 662,
            "y": 944,
            "w": 358,
            "h": 462
          }
        },
        {
          "filename": "https://powers.s3.amazonaws.com/ArgusKick2_002.png",
          "rotated": false,
          "trimmed": true,
          "sourceSize": {
            "w": 720,
            "h": 720
          },
          "spriteSourceSize": {
            "x": 249,
            "y": 201,
            "w": 397,
            "h": 466
          },
          "frame": {
            "x": 1020,
            "y": 944,
            "w": 397,
            "h": 466
          }
        },
        {
          "filename": "https://powers.s3.amazonaws.com/ArgusDie_002.png",
          "rotated": false,
          "trimmed": true,
          "sourceSize": {
            "w": 720,
            "h": 720
          },
          "spriteSourceSize": {
            "x": 168,
            "y": 276,
            "w": 401,
            "h": 314
          },
          "frame": {
            "x": 1417,
            "y": 944,
            "w": 401,
            "h": 314
          }
        },
        {
          "filename": "https://powers.s3.amazonaws.com/ArgusDie_003.png",
          "rotated": false,
          "trimmed": true,
          "sourceSize": {
            "w": 720,
            "h": 720
          },
          "spriteSourceSize": {
            "x": 116,
            "y": 391,
            "w": 439,
            "h": 254
          },
          "frame": {
            "x": 0,
            "y": 1410,
            "w": 439,
            "h": 254
          }
        },
        {
          "filename": "https://powers.s3.amazonaws.com/ArgusDie_004.png",
          "rotated": false,
          "trimmed": true,
          "sourceSize": {
            "w": 720,
            "h": 720
          },
          "spriteSourceSize": {
            "x": 102,
            "y": 463,
            "w": 465,
            "h": 191
          },
          "frame": {
            "x": 439,
            "y": 1410,
            "w": 465,
            "h": 191
          }
        },
        {
          "filename": "https://powers.s3.amazonaws.com/ArgusDie_005.png",
          "rotated": false,
          "trimmed": true,
          "sourceSize": {
            "w": 720,
            "h": 720
          },
          "spriteSourceSize": {
            "x": 91,
            "y": 545,
            "w": 478,
            "h": 137
          },
          "frame": {
            "x": 904,
            "y": 1410,
            "w": 478,
            "h": 137
          }
        },
        {
          "filename": "https://powers.s3.amazonaws.com/ArgusDie_006.png",
          "rotated": false,
          "trimmed": true,
          "sourceSize": {
            "w": 720,
            "h": 720
          },
          "spriteSourceSize": {
            "x": 81,
            "y": 550,
            "w": 483,
            "h": 127
          },
          "frame": {
            "x": 1382,
            "y": 1410,
            "w": 483,
            "h": 127
          }
        }
      ]
    },
    {
      "image": "Argus-1.png",
      "format": "RGBA8888",
      "size": {
        "w": 2006,
        "h": 1012
      },
      "scale": 1,
      "frames": [
        {
          "filename": "https://powers.s3.amazonaws.com/ArgusIdle_019.png",
          "rotated": false,
          "trimmed": true,
          "sourceSize": {
            "w": 720,
            "h": 720
          },
          "spriteSourceSize": {
            "x": 269,
            "y": 196,
            "w": 196,
            "h": 474
          },
          "frame": {
            "x": 0,
            "y": 0,
            "w": 196,
            "h": 474
          }
        },
        {
          "filename": "https://powers.s3.amazonaws.com/ArgusIdle_018.png",
          "rotated": false,
          "trimmed": true,
          "sourceSize": {
            "w": 720,
            "h": 720
          },
          "spriteSourceSize": {
            "x": 268,
            "y": 196,
            "w": 197,
            "h": 474
          },
          "frame": {
            "x": 196,
            "y": 0,
            "w": 197,
            "h": 474
          }
        },
        {
          "filename": "https://powers.s3.amazonaws.com/ArgusIdle_017.png",
          "rotated": false,
          "trimmed": true,
          "sourceSize": {
            "w": 720,
            "h": 720
          },
          "spriteSourceSize": {
            "x": 267,
            "y": 196,
            "w": 198,
            "h": 474
          },
          "frame": {
            "x": 393,
            "y": 0,
            "w": 198,
            "h": 474
          }
        },
        {
          "filename": "https://powers.s3.amazonaws.com/ArgusIdle_016.png",
          "rotated": false,
          "trimmed": true,
          "sourceSize": {
            "w": 720,
            "h": 720
          },
          "spriteSourceSize": {
            "x": 266,
            "y": 196,
            "w": 199,
            "h": 474
          },
          "frame": {
            "x": 591,
            "y": 0,
            "w": 199,
            "h": 474
          }
        },
        {
          "filename": "https://powers.s3.amazonaws.com/ArgusIdle_005.png",
          "rotated": false,
          "trimmed": true,
          "sourceSize": {
            "w": 720,
            "h": 720
          },
          "spriteSourceSize": {
            "x": 264,
            "y": 196,
            "w": 201,
            "h": 474
          },
          "frame": {
            "x": 790,
            "y": 0,
            "w": 201,
            "h": 474
          }
        },
        {
          "filename": "https://powers.s3.amazonaws.com/ArgusIdle_015.png",
          "rotated": false,
          "trimmed": true,
          "sourceSize": {
            "w": 720,
            "h": 720
          },
          "spriteSourceSize": {
            "x": 264,
            "y": 196,
            "w": 201,
            "h": 474
          },
          "frame": {
            "x": 991,
            "y": 0,
            "w": 201,
            "h": 474
          }
        },
        {
          "filename": "https://powers.s3.amazonaws.com/ArgusIdle_006.png",
          "rotated": false,
          "trimmed": true,
          "sourceSize": {
            "w": 720,
            "h": 720
          },
          "spriteSourceSize": {
            "x": 262,
            "y": 196,
            "w": 203,
            "h": 474
          },
          "frame": {
            "x": 1192,
            "y": 0,
            "w": 203,
            "h": 474
          }
        },
        {
          "filename": "https://powers.s3.amazonaws.com/ArgusIdle_014.png",
          "rotated": false,
          "trimmed": true,
          "sourceSize": {
            "w": 720,
            "h": 720
          },
          "spriteSourceSize": {
            "x": 262,
            "y": 196,
            "w": 203,
            "h": 474
          },
          "frame": {
            "x": 1395,
            "y": 0,
            "w": 203,
            "h": 474
          }
        },
        {
          "filename": "https://powers.s3.amazonaws.com/ArgusIdle_007.png",
          "rotated": false,
          "trimmed": true,
          "sourceSize": {
            "w": 720,
            "h": 720
          },
          "spriteSourceSize": {
            "x": 261,
            "y": 196,
            "w": 204,
            "h": 474
          },
          "frame": {
            "x": 1598,
            "y": 0,
            "w": 204,
            "h": 474
          }
        },
        {
          "filename": "https://powers.s3.amazonaws.com/ArgusIdle_013.png",
          "rotated": false,
          "trimmed": true,
          "sourceSize": {
            "w": 720,
            "h": 720
          },
          "spriteSourceSize": {
            "x": 261,
            "y": 196,
            "w": 204,
            "h": 474
          },
          "frame": {
            "x": 1802,
            "y": 0,
            "w": 204,
            "h": 474
          }
        },
        {
          "filename": "https://powers.s3.amazonaws.com/ArgusIdle_008.png",
          "rotated": false,
          "trimmed": true,
          "sourceSize": {
            "w": 720,
            "h": 720
          },
          "spriteSourceSize": {
            "x": 260,
            "y": 196,
            "w": 205,
            "h": 474
          },
          "frame": {
            "x": 0,
            "y": 474,
            "w": 205,
            "h": 474
          }
        },
        {
          "filename": "https://powers.s3.amazonaws.com/ArgusIdle_012.png",
          "rotated": false,
          "trimmed": true,
          "sourceSize": {
            "w": 720,
            "h": 720
          },
          "spriteSourceSize": {
            "x": 260,
            "y": 196,
            "w": 205,
            "h": 474
          },
          "frame": {
            "x": 205,
            "y": 474,
            "w": 205,
            "h": 474
          }
        },
        {
          "filename": "https://powers.s3.amazonaws.com/ArgusCast_004.png",
          "rotated": false,
          "trimmed": true,
          "sourceSize": {
            "w": 720,
            "h": 720
          },
          "spriteSourceSize": {
            "x": 271,
            "y": 138,
            "w": 205,
            "h": 534
          },
          "frame": {
            "x": 410,
            "y": 474,
            "w": 205,
            "h": 534
          }
        },
        {
          "filename": "https://powers.s3.amazonaws.com/ArgusIdle_009.png",
          "rotated": false,
          "trimmed": true,
          "sourceSize": {
            "w": 720,
            "h": 720
          },
          "spriteSourceSize": {
            "x": 259,
            "y": 196,
            "w": 206,
            "h": 474
          },
          "frame": {
            "x": 615,
            "y": 474,
            "w": 206,
            "h": 474
          }
        },
        {
          "filename": "https://powers.s3.amazonaws.com/ArgusIdle_011.png",
          "rotated": false,
          "trimmed": true,
          "sourceSize": {
            "w": 720,
            "h": 720
          },
          "spriteSourceSize": {
            "x": 259,
            "y": 196,
            "w": 206,
            "h": 474
          },
          "frame": {
            "x": 821,
            "y": 474,
            "w": 206,
            "h": 474
          }
        },
        {
          "filename": "https://powers.s3.amazonaws.com/ArgusCast_003.png",
          "rotated": false,
          "trimmed": true,
          "sourceSize": {
            "w": 720,
            "h": 720
          },
          "spriteSourceSize": {
            "x": 270,
            "y": 134,
            "w": 206,
            "h": 538
          },
          "frame": {
            "x": 1027,
            "y": 474,
            "w": 206,
            "h": 538
          }
        },
        {
          "filename": "https://powers.s3.amazonaws.com/ArgusIdle_010.png",
          "rotated": false,
          "trimmed": true,
          "sourceSize": {
            "w": 720,
            "h": 720
          },
          "spriteSourceSize": {
            "x": 258,
            "y": 196,
            "w": 207,
            "h": 474
          },
          "frame": {
            "x": 1233,
            "y": 474,
            "w": 207,
            "h": 474
          }
        },
        {
          "filename": "https://powers.s3.amazonaws.com/ArgusCast_002.png",
          "rotated": false,
          "trimmed": true,
          "sourceSize": {
            "w": 720,
            "h": 720
          },
          "spriteSourceSize": {
            "x": 269,
            "y": 144,
            "w": 207,
            "h": 528
          },
          "frame": {
            "x": 1440,
            "y": 474,
            "w": 207,
            "h": 528
          }
        },
        {
          "filename": "https://powers.s3.amazonaws.com/ArgusHit_001.png",
          "rotated": false,
          "trimmed": true,
          "sourceSize": {
            "w": 720,
            "h": 720
          },
          "spriteSourceSize": {
            "x": 265,
            "y": 203,
            "w": 227,
            "h": 475
          },
          "frame": {
            "x": 1647,
            "y": 474,
            "w": 227,
            "h": 475
          }
        }
      ]
    }
  ],
  "meta": {
    "app": "https://www.codeandweb.com/texturepacker",
    "version": "3.0",
    "smartupdate": "$TexturePacker:SmartUpdate:712e4386f9ed429cb9de536982a4c44f:621e5c310dd8b529dfa90ea6aa949b04:f11b117953d53fbd0d4e6113fd033534$"
  }
}
